simplefin_archiver/__init__.py
simplefin_archiver/api/__init__.py
simplefin_archiver/api/api.py
simplefin_archiver/cli.py
simplefin_archiver/db.py
simplefin_archiver/models.py
simplefin_archiver/schemas.py
simplefin_archiver/simplefin.py
simplefin_archiver-0.3.2.dist-info/WHEEL
simplefin_archiver-0.3.2.dist-info/entry_points.txt
simplefin_archiver-0.3.2.dist-info/METADATA
simplefin_archiver-0.3.2.dist-info/RECORD
