Metadata-Version: 2.3
Name: simplefin-archiver
Version: 0.3.2
Summary: Utility to pull and archive simplefin data
Author: Tassilo Selover-Stephan
Author-email: Tassilo Selover-Stephan <tassilo@selover-stephan.com>
Requires-Dist: alembic>=1.17.2
Requires-Dist: sqlalchemy>=2.0.0
Requires-Dist: psycopg2-binary>=2.9.11
Requires-Dist: requests>=2.32.0
Requires-Dist: typer>=0.20.0
Requires-Python: >=3.12
